anybinding/Bind.py
anybinding/__init__.py
anybinding/py.typed
anybinding-2.0.4.dist-info/LICENSE
anybinding-2.0.4.dist-info/METADATA
anybinding-2.0.4.dist-info/WHEEL
anybinding-2.0.4.dist-info/top_level.txt
anybinding-2.0.4.dist-info/RECORD
