Metadata-Version: 2.1
Name: anybinding
Version: 2.0.4
Summary: any command line program binding to python.
Home-page: https://github.com/guangrei/Anypybinding
Author: guangrei
Author-email: myawn@pm.me
License: MIT
Keywords: command binding
License-File: LICENSE
